README.rst
setup.py
arksearch/__init__.py
arksearch/arksearch.py
arksearch.egg-info/PKG-INFO
arksearch.egg-info/SOURCES.txt
arksearch.egg-info/dependency_links.txt
arksearch.egg-info/entry_points.txt
arksearch.egg-info/pbr.json
arksearch.egg-info/requires.txt
arksearch.egg-info/top_level.txt