Metadata-Version: 1.0
Name: arksearch
Version: 0.0.1
Summary: Searches Intel's ARK site for processor information
Home-page: https://github.com/major/arksearch
Author: Major Hayden
Author-email: major@mhtx.net
License: UNKNOWN
Platform: UNKNOWN
